pyosutools/__init__.py
pyosutools/datatypes.py
pyosutools/exceptions.py
pyosutools/utils.py
pyosutools/beatmap/__init__.py
pyosutools/beatmap/beatmap.py
pyosutools/database/__init__.py
pyosutools/database/collection.py
pyosutools/database/osu.py
pyosutools/database/presence.py
pyosutools/database/scores.py
pyosutools-0.2.5.dist-info/LICENSE
pyosutools-0.2.5.dist-info/METADATA
pyosutools-0.2.5.dist-info/WHEEL
pyosutools-0.2.5.dist-info/top_level.txt
pyosutools-0.2.5.dist-info/RECORD
