Metadata-Version: 2.1
Name: pyosutools
Version: 0.2.5
Summary: Parsing osu! files for easier usage
Author-email: OlegSuperBro <olegrakovic323@gmail.com>
Project-URL: Homepage, https://github.com/OlegSuperBro/pyosutools
Project-URL: Bug Tracker, https://github.com/OlegSuperBro/pyosutools/issues
Classifier: Programming Language :: Python :: 3
Classifier: License :: OSI Approved :: MIT License
Classifier: Operating System :: OS Independent
Requires-Python: >=3.7
License-File: LICENSE
Requires-Dist: aenum ==3.1.15
